[
    {
        "projectName": "HeyCart",
        "description": "HeyCart is an e-commerce website that sells grocery items. On HeyCart, buyer can do login/signup, choose items from multiple categories, add these products to the cart and go for the checkout.",
        "image": "heyCartImage",
        "technologies": "React.js, Redux, HTML, CSS, Express.js, MongoDB, JWT",
        "githubLink": "",
        "liveLink": ""
    },

    {
        "projectName": "Web Portfolio",
        "description": "This is my portfolio website developed to showcase my skills, experiences and projects.",
        "image": "myPortfolio",
        "technologies": "Next.js, React.js, Material UI",
        "githubLink": "",
        "liveLink": ""
    },

    {
        "projectName": "TripTales",
        "description": "HeyCart is an e-commerce website that sells grocery items. On HeyCart, buyer can do login/signup, choose items from multiple categories, add these products to the cart and go for the checkout.",
        "image": "heyCartImage",
        "technologies": "React.js, Redux, HTML, CSS, Express.js, MongoDB, JWT",
        "githubLink": "",
        "liveLink": ""
    }
]